{"gameDetails":{"round":73,"maxRounds":400,"mapWidth":16,"mapHeight":8,"roundIncomeEnergy":5,"buildingPrices":{"ENERGY":20,"ATTACK":30,"TESLA":100,"DEFENSE":30},"buildingsStats":{"ENERGY":{"health":5,"constructionTime":1,"price":20,"weaponDamage":0,"weaponSpeed":0,"weaponCooldownPeriod":0,"energyGeneratedPerTurn":3,"destroyMultiplier":1,"constructionScore":3},"ATTACK":{"health":5,"constructionTime":1,"price":30,"weaponDamage":5,"weaponSpeed":2,"weaponCooldownPeriod":3,"energyGeneratedPerTurn":0,"destroyMultiplier":1,"constructionScore":4},"TESLA":{"health":5,"constructionTime":10,"price":100,"weaponDamage":20,"weaponSpeed":0,"weaponCooldownPeriod":10,"energyGeneratedPerTurn":0,"destroyMultiplier":10,"constructionScore":20},"DEFENSE":{"health":20,"constructionTime":3,"price":30,"weaponDamage":0,"weaponSpeed":0,"weaponCooldownPeriod":0,"energyGeneratedPerTurn":0,"destroyMultiplier":1,"constructionScore":10}},"ironCurtainStats":{"activeRounds":6,"resetPeriod":30,"price":100,"constructionScore":20}},"players":[{"playerType":"B","energy":30,"health":35,"hitsTaken":13,"score":3052,"ironCurtainAvailable":false,"activeIronCurtainLifetime":1,"isIronCurtainActive":true},{"playerType":"A","energy":28,"health":65,"hitsTaken":7,"score":3589,"ironCurtainAvailable":true,"activeIronCurtainLifetime":-13,"isIronCurtainActive":false}],"gameMap":[[{"x":0,"y":0,"buildings":[{"health":5,"constructionTimeLeft":-72,"price":20,"weaponDamage":0,"weaponSpeed":0,"weaponCooldownTimeLeft":0,"weaponCooldownPeriod":0,"destroyMultiplier":1,"constructionScore":3,"energyGeneratedPerTurn":3,"maxRange":0,"buildingType":"ENERGY","energyPerShot":0,"x":0,"y":0,"playerType":"A"}],"missiles":[],"cellOwner":"A"},{"x":1,"y":0,"buildings":[{"health":5,"constructionTimeLeft":-29,"price":30,"weaponDamage":5,"weaponSpeed":2,"weaponCooldownTimeLeft":3,"weaponCooldownPeriod":3,"destroyMultiplier":1,"constructionScore":4,"energyGeneratedPerTurn":0,"maxRange":0,"buildingType":"ATTACK","energyPerShot":0,"x":1,"y":0,"playerType":"A"}],"missiles":[],"cellOwner":"A"},{"x":2,"y":0,"buildings":[],"missiles":[],"cellOwner":"A"},{"x":3,"y":0,"buildings":[],"missiles":[{"damage":5,"speed":2,"id":"d8bb03aa-bc67-4371-83bc-5202128bab6a","x":3,"y":0,"playerType":"A"}],"cellOwner":"A"},{"x":4,"y":0,"buildings":[],"missiles":[],"cellOwner":"A"},{"x":5,"y":0,"buildings":[{"health":10,"constructionTimeLeft":-6,"price":30,"weaponDamage":0,"weaponSpeed":0,"weaponCooldownTimeLeft":0,"weaponCooldownPeriod":0,"destroyMultiplier":1,"constructionScore":10,"energyGeneratedPerTurn":0,"maxRange":0,"buildingType":"DEFENSE","energyPerShot":0,"x":5,"y":0,"playerType":"A"}],"missiles":[],"cellOwner":"A"},{"x":6,"y":0,"buildings":[],"missiles":[{"damage":5,"speed":2,"id":"ecc92159-666a-4272-820b-53d165df704f","x":6,"y":0,"playerType":"B"}],"cellOwner":"A"},{"x":7,"y":0,"buildings":[],"missiles":[],"cellOwner":"A"},{"x":8,"y":0,"buildings":[],"missiles":[{"damage":5,"speed":2,"id":"f79cde25-0026-43c7-91e7-029ca566adca","x":8,"y":0,"playerType":"B"}],"cellOwner":"B"},{"x":9,"y":0,"buildings":[{"health":10,"constructionTimeLeft":-10,"price":30,"weaponDamage":0,"weaponSpeed":0,"weaponCooldownTimeLeft":0,"weaponCooldownPeriod":0,"destroyMultiplier":1,"constructionScore":10,"energyGeneratedPerTurn":0,"maxRange":0,"buildingType":"DEFENSE","energyPerShot":0,"x":9,"y":0,"playerType":"B"}],"missiles":[],"cellOwner":"B"},{"x":10,"y":0,"buildings":[],"missiles":[],"cellOwner":"B"},{"x":11,"y":0,"buildings":[],"missiles":[],"cellOwner":"B"},{"x":12,"y":0,"buildings":[{"health":5,"constructionTimeLeft":-38,"price":30,"weaponDamage":5,"weaponSpeed":2,"weaponCooldownTimeLeft":2,"weaponCooldownPeriod":3,"destroyMultiplier":1,"constructionScore":4,"energyGeneratedPerTurn":0,"maxRange":0,"buildingType":"ATTACK","energyPerShot":0,"x":12,"y":0,"playerType":"B"}],"missiles":[],"cellOwner":"B"},{"x":13,"y":0,"buildings":[],"missiles":[],"cellOwner":"B"},{"x":14,"y":0,"buildings":[{"health":5,"constructionTimeLeft":-16,"price":30,"weaponDamage":5,"weaponSpeed":2,"weaponCooldownTimeLeft":0,"weaponCooldownPeriod":3,"destroyMultiplier":1,"constructionScore":4,"energyGeneratedPerTurn":0,"maxRange":0,"buildingType":"ATTACK","energyPerShot":0,"x":14,"y":0,"playerType":"B"}],"missiles":[],"cellOwner":"B"},{"x":15,"y":0,"buildings":[{"health":5,"constructionTimeLeft":-72,"price":20,"weaponDamage":0,"weaponSpeed":0,"weaponCooldownTimeLeft":0,"weaponCooldownPeriod":0,"destroyMultiplier":1,"constructionScore":3,"energyGeneratedPerTurn":3,"maxRange":0,"buildingType":"ENERGY","energyPerShot":0,"x":15,"y":0,"playerType":"B"}],"missiles":[],"cellOwner":"B"}],[{"x":0,"y":1,"buildings":[{"health":5,"constructionTimeLeft":-69,"price":20,"weaponDamage":0,"weaponSpeed":0,"weaponCooldownTimeLeft":0,"weaponCooldownPeriod":0,"destroyMultiplier":1,"constructionScore":3,"energyGeneratedPerTurn":3,"maxRange":0,"buildingType":"ENERGY","energyPerShot":0,"x":0,"y":1,"playerType":"A"}],"missiles":[],"cellOwner":"A"},{"x":1,"y":1,"buildings":[],"missiles":[],"cellOwner":"A"},{"x":2,"y":1,"buildings":[],"missiles":[],"cellOwner":"A"},{"x":3,"y":1,"buildings":[{"health":5,"constructionTimeLeft":-15,"price":20,"weaponDamage":0,"weaponSpeed":0,"weaponCooldownTimeLeft":0,"weaponCooldownPeriod":0,"destroyMultiplier":1,"constructionScore":3,"energyGeneratedPerTurn":3,"maxRange":0,"buildingType":"ENERGY","energyPerShot":0,"x":3,"y":1,"playerType":"A"}],"missiles":[],"cellOwner":"A"},{"x":4,"y":1,"buildings":[{"health":5,"constructionTimeLeft":-21,"price":30,"weaponDamage":5,"weaponSpeed":2,"weaponCooldownTimeLeft":3,"weaponCooldownPeriod":3,"destroyMultiplier":1,"constructionScore":4,"energyGeneratedPerTurn":0,"maxRange":0,"buildingType":"ATTACK","energyPerShot":0,"x":4,"y":1,"playerType":"A"}],"missiles":[],"cellOwner":"A"},{"x":5,"y":1,"buildings":[],"missiles":[],"cellOwner":"A"},{"x":6,"y":1,"buildings":[],"missiles":[{"damage":5,"speed":2,"id":"7d8b6301-9b64-4b2f-8a11-048080c8cb14","x":6,"y":1,"playerType":"A"}],"cellOwner":"A"},{"x":7,"y":1,"buildings":[{"health":5,"constructionTimeLeft":-1,"price":20,"weaponDamage":0,"weaponSpeed":0,"weaponCooldownTimeLeft":0,"weaponCooldownPeriod":0,"destroyMultiplier":1,"constructionScore":3,"energyGeneratedPerTurn":3,"maxRange":0,"buildingType":"ENERGY","energyPerShot":0,"x":7,"y":1,"playerType":"A"}],"missiles":[],"cellOwner":"A"},{"x":8,"y":1,"buildings":[{"health":5,"constructionTimeLeft":-9,"price":30,"weaponDamage":0,"weaponSpeed":0,"weaponCooldownTimeLeft":0,"weaponCooldownPeriod":0,"destroyMultiplier":1,"constructionScore":10,"energyGeneratedPerTurn":0,"maxRange":0,"buildingType":"DEFENSE","energyPerShot":0,"x":8,"y":1,"playerType":"B"}],"missiles":[],"cellOwner":"B"},{"x":9,"y":1,"buildings":[],"missiles":[],"cellOwner":"B"},{"x":10,"y":1,"buildings":[{"health":5,"constructionTimeLeft":-8,"price":30,"weaponDamage":5,"weaponSpeed":2,"weaponCooldownTimeLeft":0,"weaponCooldownPeriod":3,"destroyMultiplier":1,"constructionScore":4,"energyGeneratedPerTurn":0,"maxRange":0,"buildingType":"ATTACK","energyPerShot":0,"x":10,"y":1,"playerType":"B"}],"missiles":[],"cellOwner":"B"},{"x":11,"y":1,"buildings":[],"missiles":[],"cellOwner":"B"},{"x":12,"y":1,"buildings":[],"missiles":[{"damage":5,"speed":2,"id":"36393bc2-20eb-49af-928e-c5e3a05e38eb","x":12,"y":1,"playerType":"B"}],"cellOwner":"B"},{"x":13,"y":1,"buildings":[],"missiles":[],"cellOwner":"B"},{"x":14,"y":1,"buildings":[{"health":5,"constructionTimeLeft":-9,"price":30,"weaponDamage":5,"weaponSpeed":2,"weaponCooldownTimeLeft":3,"weaponCooldownPeriod":3,"destroyMultiplier":1,"constructionScore":4,"energyGeneratedPerTurn":0,"maxRange":0,"buildingType":"ATTACK","energyPerShot":0,"x":14,"y":1,"playerType":"B"}],"missiles":[],"cellOwner":"B"},{"x":15,"y":1,"buildings":[{"health":5,"constructionTimeLeft":-41,"price":20,"weaponDamage":0,"weaponSpeed":0,"weaponCooldownTimeLeft":0,"weaponCooldownPeriod":0,"destroyMultiplier":1,"constructionScore":3,"energyGeneratedPerTurn":3,"maxRange":0,"buildingType":"ENERGY","energyPerShot":0,"x":15,"y":1,"playerType":"B"}],"missiles":[],"cellOwner":"B"}],[{"x":0,"y":2,"buildings":[{"health":5,"constructionTimeLeft":-23,"price":30,"weaponDamage":5,"weaponSpeed":2,"weaponCooldownTimeLeft":1,"weaponCooldownPeriod":3,"destroyMultiplier":1,"constructionScore":4,"energyGeneratedPerTurn":0,"maxRange":0,"buildingType":"ATTACK","energyPerShot":0,"x":0,"y":2,"playerType":"A"}],"missiles":[],"cellOwner":"A"},{"x":1,"y":2,"buildings":[{"health":5,"constructionTimeLeft":-4,"price":30,"weaponDamage":5,"weaponSpeed":2,"weaponCooldownTimeLeft":0,"weaponCooldownPeriod":3,"destroyMultiplier":1,"constructionScore":4,"energyGeneratedPerTurn":0,"maxRange":0,"buildingType":"ATTACK","energyPerShot":0,"x":1,"y":2,"playerType":"A"}],"missiles":[],"cellOwner":"A"},{"x":2,"y":2,"buildings":[{"health":5,"constructionTimeLeft":-22,"price":30,"weaponDamage":5,"weaponSpeed":2,"weaponCooldownTimeLeft":2,"weaponCooldownPeriod":3,"destroyMultiplier":1,"constructionScore":4,"energyGeneratedPerTurn":0,"maxRange":0,"buildingType":"ATTACK","energyPerShot":0,"x":2,"y":2,"playerType":"A"}],"missiles":[],"cellOwner":"A"},{"x":3,"y":2,"buildings":[{"health":5,"constructionTimeLeft":-38,"price":30,"weaponDamage":5,"weaponSpeed":2,"weaponCooldownTimeLeft":2,"weaponCooldownPeriod":3,"destroyMultiplier":1,"constructionScore":4,"energyGeneratedPerTurn":0,"maxRange":0,"buildingType":"ATTACK","energyPerShot":0,"x":3,"y":2,"playerType":"A"}],"missiles":[],"cellOwner":"A"},{"x":4,"y":2,"buildings":[{"health":5,"constructionTimeLeft":-3,"price":30,"weaponDamage":5,"weaponSpeed":2,"weaponCooldownTimeLeft":1,"weaponCooldownPeriod":3,"destroyMultiplier":1,"constructionScore":4,"energyGeneratedPerTurn":0,"maxRange":0,"buildingType":"ATTACK","energyPerShot":0,"x":4,"y":2,"playerType":"A"}],"missiles":[],"cellOwner":"A"},{"x":5,"y":2,"buildings":[{"health":10,"constructionTimeLeft":-14,"price":30,"weaponDamage":0,"weaponSpeed":0,"weaponCooldownTimeLeft":0,"weaponCooldownPeriod":0,"destroyMultiplier":1,"constructionScore":10,"energyGeneratedPerTurn":0,"maxRange":0,"buildingType":"DEFENSE","energyPerShot":0,"x":5,"y":2,"playerType":"A"}],"missiles":[],"cellOwner":"A"},{"x":6,"y":2,"buildings":[{"health":5,"constructionTimeLeft":-5,"price":30,"weaponDamage":5,"weaponSpeed":2,"weaponCooldownTimeLeft":3,"weaponCooldownPeriod":3,"destroyMultiplier":1,"constructionScore":4,"energyGeneratedPerTurn":0,"maxRange":0,"buildingType":"ATTACK","energyPerShot":0,"x":6,"y":2,"playerType":"A"}],"missiles":[{"damage":5,"speed":2,"id":"74cf1f7d-c7d7-4dcc-951f-5ae6e448ed13","x":6,"y":2,"playerType":"A"},{"damage":5,"speed":2,"id":"e5e4b27e-fce1-4bba-a1f6-3bd6699daab8","x":6,"y":2,"playerType":"A"}],"cellOwner":"A"},{"x":7,"y":2,"buildings":[{"health":5,"constructionTimeLeft":-2,"price":30,"weaponDamage":5,"weaponSpeed":2,"weaponCooldownTimeLeft":2,"weaponCooldownPeriod":3,"destroyMultiplier":1,"constructionScore":4,"energyGeneratedPerTurn":0,"maxRange":0,"buildingType":"ATTACK","energyPerShot":0,"x":7,"y":2,"playerType":"A"}],"missiles":[{"damage":5,"speed":2,"id":"639b654b-9f9a-4728-bc36-b18ee88fdfc9","x":7,"y":2,"playerType":"A"}],"cellOwner":"A"},{"x":8,"y":2,"buildings":[{"health":20,"constructionTimeLeft":1,"price":30,"weaponDamage":0,"weaponSpeed":0,"weaponCooldownTimeLeft":0,"weaponCooldownPeriod":0,"destroyMultiplier":1,"constructionScore":10,"energyGeneratedPerTurn":0,"maxRange":0,"buildingType":"DEFENSE","energyPerShot":0,"x":8,"y":2,"playerType":"B"}],"missiles":[],"cellOwner":"B"},{"x":9,"y":2,"buildings":[{"health":20,"constructionTimeLeft":-3,"price":30,"weaponDamage":0,"weaponSpeed":0,"weaponCooldownTimeLeft":0,"weaponCooldownPeriod":0,"destroyMultiplier":1,"constructionScore":10,"energyGeneratedPerTurn":0,"maxRange":0,"buildingType":"DEFENSE","energyPerShot":0,"x":9,"y":2,"playerType":"B"}],"missiles":[],"cellOwner":"B"},{"x":10,"y":2,"buildings":[{"health":5,"constructionTimeLeft":0,"price":30,"weaponDamage":5,"weaponSpeed":2,"weaponCooldownTimeLeft":0,"weaponCooldownPeriod":3,"destroyMultiplier":1,"constructionScore":4,"energyGeneratedPerTurn":0,"maxRange":0,"buildingType":"ATTACK","energyPerShot":0,"x":10,"y":2,"playerType":"B"}],"missiles":[],"cellOwner":"B"},{"x":11,"y":2,"buildings":[{"health":5,"constructionTimeLeft":-3,"price":20,"weaponDamage":0,"weaponSpeed":0,"weaponCooldownTimeLeft":0,"weaponCooldownPeriod":0,"destroyMultiplier":1,"constructionScore":3,"energyGeneratedPerTurn":3,"maxRange":0,"buildingType":"ENERGY","energyPerShot":0,"x":11,"y":2,"playerType":"B"}],"missiles":[{"damage":5,"speed":2,"id":"dfe6e065-b827-40c8-92da-25678825effe","x":11,"y":2,"playerType":"B"}],"cellOwner":"B"},{"x":12,"y":2,"buildings":[],"missiles":[],"cellOwner":"B"},{"x":13,"y":2,"buildings":[],"missiles":[],"cellOwner":"B"},{"x":14,"y":2,"buildings":[],"missiles":[],"cellOwner":"B"},{"x":15,"y":2,"buildings":[{"health":5,"constructionTimeLeft":-2,"price":30,"weaponDamage":5,"weaponSpeed":2,"weaponCooldownTimeLeft":2,"weaponCooldownPeriod":3,"destroyMultiplier":1,"constructionScore":4,"energyGeneratedPerTurn":0,"maxRange":0,"buildingType":"ATTACK","energyPerShot":0,"x":15,"y":2,"playerType":"B"}],"missiles":[],"cellOwner":"B"}],[{"x":0,"y":3,"buildings":[],"missiles":[],"cellOwner":"A"},{"x":1,"y":3,"buildings":[],"missiles":[],"cellOwner":"A"},{"x":2,"y":3,"buildings":[],"missiles":[],"cellOwner":"A"},{"x":3,"y":3,"buildings":[{"health":20,"constructionTimeLeft":-4,"price":30,"weaponDamage":0,"weaponSpeed":0,"weaponCooldownTimeLeft":0,"weaponCooldownPeriod":0,"destroyMultiplier":1,"constructionScore":10,"energyGeneratedPerTurn":0,"maxRange":0,"buildingType":"DEFENSE","energyPerShot":0,"x":3,"y":3,"playerType":"A"}],"missiles":[],"cellOwner":"A"},{"x":4,"y":3,"buildings":[],"missiles":[],"cellOwner":"A"},{"x":5,"y":3,"buildings":[],"missiles":[],"cellOwner":"A"},{"x":6,"y":3,"buildings":[],"missiles":[],"cellOwner":"A"},{"x":7,"y":3,"buildings":[],"missiles":[{"damage":5,"speed":2,"id":"08a8cd73-0904-4f63-80f5-b0d35f72929f","x":7,"y":3,"playerType":"B"}],"cellOwner":"A"},{"x":8,"y":3,"buildings":[{"health":5,"constructionTimeLeft":-21,"price":30,"weaponDamage":0,"weaponSpeed":0,"weaponCooldownTimeLeft":0,"weaponCooldownPeriod":0,"destroyMultiplier":1,"constructionScore":10,"energyGeneratedPerTurn":0,"maxRange":0,"buildingType":"DEFENSE","energyPerShot":0,"x":8,"y":3,"playerType":"B"}],"missiles":[{"damage":5,"speed":2,"id":"fec87835-24b7-4850-a70d-4e533c73d5e6","x":8,"y":3,"playerType":"B"}],"cellOwner":"B"},{"x":9,"y":3,"buildings":[{"health":5,"constructionTimeLeft":-28,"price":20,"weaponDamage":0,"weaponSpeed":0,"weaponCooldownTimeLeft":0,"weaponCooldownPeriod":0,"destroyMultiplier":1,"constructionScore":3,"energyGeneratedPerTurn":3,"maxRange":0,"buildingType":"ENERGY","energyPerShot":0,"x":9,"y":3,"playerType":"B"}],"missiles":[],"cellOwner":"B"},{"x":10,"y":3,"buildings":[{"health":5,"constructionTimeLeft":-29,"price":30,"weaponDamage":5,"weaponSpeed":2,"weaponCooldownTimeLeft":3,"weaponCooldownPeriod":3,"destroyMultiplier":1,"constructionScore":4,"energyGeneratedPerTurn":0,"maxRange":0,"buildingType":"ATTACK","energyPerShot":0,"x":10,"y":3,"playerType":"B"}],"missiles":[],"cellOwner":"B"},{"x":11,"y":3,"buildings":[{"health":5,"constructionTimeLeft":-22,"price":30,"weaponDamage":5,"weaponSpeed":2,"weaponCooldownTimeLeft":2,"weaponCooldownPeriod":3,"destroyMultiplier":1,"constructionScore":4,"energyGeneratedPerTurn":0,"maxRange":0,"buildingType":"ATTACK","energyPerShot":0,"x":11,"y":3,"playerType":"B"}],"missiles":[],"cellOwner":"B"},{"x":12,"y":3,"buildings":[],"missiles":[],"cellOwner":"B"},{"x":13,"y":3,"buildings":[],"missiles":[],"cellOwner":"B"},{"x":14,"y":3,"buildings":[],"missiles":[],"cellOwner":"B"},{"x":15,"y":3,"buildings":[{"health":5,"constructionTimeLeft":-20,"price":20,"weaponDamage":0,"weaponSpeed":0,"weaponCooldownTimeLeft":0,"weaponCooldownPeriod":0,"destroyMultiplier":1,"constructionScore":3,"energyGeneratedPerTurn":3,"maxRange":0,"buildingType":"ENERGY","energyPerShot":0,"x":15,"y":3,"playerType":"B"}],"missiles":[],"cellOwner":"B"}],[{"x":0,"y":4,"buildings":[{"health":5,"constructionTimeLeft":-63,"price":20,"weaponDamage":0,"weaponSpeed":0,"weaponCooldownTimeLeft":0,"weaponCooldownPeriod":0,"destroyMultiplier":1,"constructionScore":3,"energyGeneratedPerTurn":3,"maxRange":0,"buildingType":"ENERGY","energyPerShot":0,"x":0,"y":4,"playerType":"A"}],"missiles":[],"cellOwner":"A"},{"x":1,"y":4,"buildings":[],"missiles":[],"cellOwner":"A"},{"x":2,"y":4,"buildings":[{"health":5,"constructionTimeLeft":-36,"price":30,"weaponDamage":5,"weaponSpeed":2,"weaponCooldownTimeLeft":0,"weaponCooldownPeriod":3,"destroyMultiplier":1,"constructionScore":4,"energyGeneratedPerTurn":0,"maxRange":0,"buildingType":"ATTACK","energyPerShot":0,"x":2,"y":4,"playerType":"A"}],"missiles":[],"cellOwner":"A"},{"x":3,"y":4,"buildings":[],"missiles":[],"cellOwner":"A"},{"x":4,"y":4,"buildings":[],"missiles":[],"cellOwner":"A"},{"x":5,"y":4,"buildings":[],"missiles":[],"cellOwner":"A"},{"x":6,"y":4,"buildings":[{"health":20,"constructionTimeLeft":2,"price":30,"weaponDamage":0,"weaponSpeed":0,"weaponCooldownTimeLeft":0,"weaponCooldownPeriod":0,"destroyMultiplier":1,"constructionScore":10,"energyGeneratedPerTurn":0,"maxRange":0,"buildingType":"DEFENSE","energyPerShot":0,"x":6,"y":4,"playerType":"A"}],"missiles":[{"damage":5,"speed":2,"id":"7a2d0a20-3287-4fa2-b3ab-a135399c8390","x":6,"y":4,"playerType":"B"}],"cellOwner":"A"},{"x":7,"y":4,"buildings":[],"missiles":[],"cellOwner":"A"},{"x":8,"y":4,"buildings":[],"missiles":[],"cellOwner":"B"},{"x":9,"y":4,"buildings":[],"missiles":[],"cellOwner":"B"},{"x":10,"y":4,"buildings":[],"missiles":[],"cellOwner":"B"},{"x":11,"y":4,"buildings":[{"health":5,"constructionTimeLeft":-26,"price":20,"weaponDamage":0,"weaponSpeed":0,"weaponCooldownTimeLeft":0,"weaponCooldownPeriod":0,"destroyMultiplier":1,"constructionScore":3,"energyGeneratedPerTurn":3,"maxRange":0,"buildingType":"ENERGY","energyPerShot":0,"x":11,"y":4,"playerType":"B"}],"missiles":[{"damage":5,"speed":2,"id":"c6786b44-e75e-425e-88df-2ee2cbcfc512","x":11,"y":4,"playerType":"B"}],"cellOwner":"B"},{"x":12,"y":4,"buildings":[{"health":5,"constructionTimeLeft":-43,"price":30,"weaponDamage":5,"weaponSpeed":2,"weaponCooldownTimeLeft":1,"weaponCooldownPeriod":3,"destroyMultiplier":1,"constructionScore":4,"energyGeneratedPerTurn":0,"maxRange":0,"buildingType":"ATTACK","energyPerShot":0,"x":12,"y":4,"playerType":"B"}],"missiles":[],"cellOwner":"B"},{"x":13,"y":4,"buildings":[],"missiles":[],"cellOwner":"B"},{"x":14,"y":4,"buildings":[],"missiles":[],"cellOwner":"B"},{"x":15,"y":4,"buildings":[{"health":5,"constructionTimeLeft":-30,"price":30,"weaponDamage":5,"weaponSpeed":2,"weaponCooldownTimeLeft":2,"weaponCooldownPeriod":3,"destroyMultiplier":1,"constructionScore":4,"energyGeneratedPerTurn":0,"maxRange":0,"buildingType":"ATTACK","energyPerShot":0,"x":15,"y":4,"playerType":"B"}],"missiles":[],"cellOwner":"B"}],[{"x":0,"y":5,"buildings":[],"missiles":[],"cellOwner":"A"},{"x":1,"y":5,"buildings":[],"missiles":[],"cellOwner":"A"},{"x":2,"y":5,"buildings":[],"missiles":[],"cellOwner":"A"},{"x":3,"y":5,"buildings":[{"health":15,"constructionTimeLeft":-7,"price":30,"weaponDamage":0,"weaponSpeed":0,"weaponCooldownTimeLeft":0,"weaponCooldownPeriod":0,"destroyMultiplier":1,"constructionScore":10,"energyGeneratedPerTurn":0,"maxRange":0,"buildingType":"DEFENSE","energyPerShot":0,"x":3,"y":5,"playerType":"A"}],"missiles":[],"cellOwner":"A"},{"x":4,"y":5,"buildings":[],"missiles":[],"cellOwner":"A"},{"x":5,"y":5,"buildings":[],"missiles":[],"cellOwner":"A"},{"x":6,"y":5,"buildings":[],"missiles":[],"cellOwner":"A"},{"x":7,"y":5,"buildings":[],"missiles":[{"damage":5,"speed":2,"id":"dce23314-0bab-4ed0-a556-d1bd22ea9972","x":7,"y":5,"playerType":"B"}],"cellOwner":"A"},{"x":8,"y":5,"buildings":[],"missiles":[],"cellOwner":"B"},{"x":9,"y":5,"buildings":[{"health":10,"constructionTimeLeft":-16,"price":30,"weaponDamage":0,"weaponSpeed":0,"weaponCooldownTimeLeft":0,"weaponCooldownPeriod":0,"destroyMultiplier":1,"constructionScore":10,"energyGeneratedPerTurn":0,"maxRange":0,"buildingType":"DEFENSE","energyPerShot":0,"x":9,"y":5,"playerType":"B"}],"missiles":[],"cellOwner":"B"},{"x":10,"y":5,"buildings":[],"missiles":[],"cellOwner":"B"},{"x":11,"y":5,"buildings":[],"missiles":[],"cellOwner":"B"},{"x":12,"y":5,"buildings":[],"missiles":[],"cellOwner":"B"},{"x":13,"y":5,"buildings":[{"health":5,"constructionTimeLeft":-59,"price":30,"weaponDamage":5,"weaponSpeed":2,"weaponCooldownTimeLeft":1,"weaponCooldownPeriod":3,"destroyMultiplier":1,"constructionScore":4,"energyGeneratedPerTurn":0,"maxRange":0,"buildingType":"ATTACK","energyPerShot":0,"x":13,"y":5,"playerType":"B"}],"missiles":[],"cellOwner":"B"},{"x":14,"y":5,"buildings":[{"health":5,"constructionTimeLeft":-44,"price":20,"weaponDamage":0,"weaponSpeed":0,"weaponCooldownTimeLeft":0,"weaponCooldownPeriod":0,"destroyMultiplier":1,"constructionScore":3,"energyGeneratedPerTurn":3,"maxRange":0,"buildingType":"ENERGY","energyPerShot":0,"x":14,"y":5,"playerType":"B"}],"missiles":[],"cellOwner":"B"},{"x":15,"y":5,"buildings":[{"health":5,"constructionTimeLeft":-62,"price":20,"weaponDamage":0,"weaponSpeed":0,"weaponCooldownTimeLeft":0,"weaponCooldownPeriod":0,"destroyMultiplier":1,"constructionScore":3,"energyGeneratedPerTurn":3,"maxRange":0,"buildingType":"ENERGY","energyPerShot":0,"x":15,"y":5,"playerType":"B"}],"missiles":[],"cellOwner":"B"}],[{"x":0,"y":6,"buildings":[],"missiles":[],"cellOwner":"A"},{"x":1,"y":6,"buildings":[],"missiles":[],"cellOwner":"A"},{"x":2,"y":6,"buildings":[],"missiles":[],"cellOwner":"A"},{"x":3,"y":6,"buildings":[],"missiles":[],"cellOwner":"A"},{"x":4,"y":6,"buildings":[],"missiles":[],"cellOwner":"A"},{"x":5,"y":6,"buildings":[],"missiles":[],"cellOwner":"A"},{"x":6,"y":6,"buildings":[{"health":5,"constructionTimeLeft":-7,"price":20,"weaponDamage":0,"weaponSpeed":0,"weaponCooldownTimeLeft":0,"weaponCooldownPeriod":0,"destroyMultiplier":1,"constructionScore":3,"energyGeneratedPerTurn":3,"maxRange":0,"buildingType":"ENERGY","energyPerShot":0,"x":6,"y":6,"playerType":"A"}],"missiles":[],"cellOwner":"A"},{"x":7,"y":6,"buildings":[],"missiles":[],"cellOwner":"A"},{"x":8,"y":6,"buildings":[],"missiles":[],"cellOwner":"B"},{"x":9,"y":6,"buildings":[],"missiles":[],"cellOwner":"B"},{"x":10,"y":6,"buildings":[],"missiles":[],"cellOwner":"B"},{"x":11,"y":6,"buildings":[],"missiles":[],"cellOwner":"B"},{"x":12,"y":6,"buildings":[],"missiles":[],"cellOwner":"B"},{"x":13,"y":6,"buildings":[],"missiles":[],"cellOwner":"B"},{"x":14,"y":6,"buildings":[],"missiles":[],"cellOwner":"B"},{"x":15,"y":6,"buildings":[],"missiles":[],"cellOwner":"B"}],[{"x":0,"y":7,"buildings":[{"health":5,"constructionTimeLeft":-60,"price":20,"weaponDamage":0,"weaponSpeed":0,"weaponCooldownTimeLeft":0,"weaponCooldownPeriod":0,"destroyMultiplier":1,"constructionScore":3,"energyGeneratedPerTurn":3,"maxRange":0,"buildingType":"ENERGY","energyPerShot":0,"x":0,"y":7,"playerType":"A"}],"missiles":[],"cellOwner":"A"},{"x":1,"y":7,"buildings":[{"health":20,"constructionTimeLeft":-42,"price":30,"weaponDamage":0,"weaponSpeed":0,"weaponCooldownTimeLeft":0,"weaponCooldownPeriod":0,"destroyMultiplier":1,"constructionScore":10,"energyGeneratedPerTurn":0,"maxRange":0,"buildingType":"DEFENSE","energyPerShot":0,"x":1,"y":7,"playerType":"A"}],"missiles":[],"cellOwner":"A"},{"x":2,"y":7,"buildings":[],"missiles":[],"cellOwner":"A"},{"x":3,"y":7,"buildings":[],"missiles":[],"cellOwner":"A"},{"x":4,"y":7,"buildings":[],"missiles":[],"cellOwner":"A"},{"x":5,"y":7,"buildings":[],"missiles":[],"cellOwner":"A"},{"x":6,"y":7,"buildings":[],"missiles":[],"cellOwner":"A"},{"x":7,"y":7,"buildings":[],"missiles":[],"cellOwner":"A"},{"x":8,"y":7,"buildings":[],"missiles":[],"cellOwner":"B"},{"x":9,"y":7,"buildings":[],"missiles":[],"cellOwner":"B"},{"x":10,"y":7,"buildings":[],"missiles":[],"cellOwner":"B"},{"x":11,"y":7,"buildings":[],"missiles":[],"cellOwner":"B"},{"x":12,"y":7,"buildings":[],"missiles":[],"cellOwner":"B"},{"x":13,"y":7,"buildings":[],"missiles":[],"cellOwner":"B"},{"x":14,"y":7,"buildings":[],"missiles":[],"cellOwner":"B"},{"x":15,"y":7,"buildings":[],"missiles":[],"cellOwner":"B"}]],"teslaHitList":[],"ironCurtainHitList":[{"x":7,"y":2,"playerType":"B"},{"x":7,"y":1,"playerType":"B"},{"x":7,"y":2,"playerType":"B"}]}